quese
