Metadata-Version: 2.1
Name: quese
Version: 0.1.2
Summary: Package that make easier the searching process in pyhton, through Embeddings and Semantic Similarity
Author: Arnau Canela
Author-email: arnau.canela22@gmail.com
License: MIT
Keywords: searching,search,embeddings,intelligent search,similarity search,embedding search,sentence transformer search,searcher,semantic similarity,sentence similarity
License-File: LICENSE
